virus_simulation/2d.py
virus_simulation/3d.py
virus_simulation/__init__.py
virus_simulation/__main__.py
virus_simulation/any-dimension.py
virus_simulation-1.1.0.dist-info/METADATA
virus_simulation-1.1.0.dist-info/WHEEL
virus_simulation-1.1.0.dist-info/RECORD
