Metadata-Version: 2.4
Name: virus-simulation
Version: 1.1.0
Summary: Virus simulation
Author: Anvarys
Author-email: 105349498+Anvarys@users.noreply.github.com
Requires-Python: >=3.13
Classifier: Programming Language :: Python :: 3
Classifier: Programming Language :: Python :: 3.13
Classifier: Programming Language :: Python :: 3.14
Requires-Dist: matplotlib (>=3.10.7,<4.0.0)
Requires-Dist: numpy (>=2.3.4,<3.0.0)
